{
  "parent": "minecraft:recipes/root",
  "criteria": {
    "has_the_recipe": {
      "conditions": {
        "recipe": "endgameenhanced:pure_nourishing_essence"
      },
      "trigger": "minecraft:recipe_unlocked"
    },
    "has_tier_two_hunger_totem": {
      "conditions": {
        "items": [
          {
            "items": [
              "endgameenhanced:tier_two_hunger_totem"
            ]
          }
        ]
      },
      "trigger": "minecraft:inventory_changed"
    }
  },
  "requirements": [
    [
      "has_the_recipe",
      "has_tier_two_hunger_totem"
    ]
  ],
  "rewards": {
    "recipes": [
      "endgameenhanced:pure_nourishing_essence"
    ]
  }
}